falcon_auth/__init__.py
falcon_auth/backends.py
falcon_auth/middleware.py
falcon_auth/serializer.py
falcon_auth-1.0.3.dist-info/DESCRIPTION.rst
falcon_auth-1.0.3.dist-info/METADATA
falcon_auth-1.0.3.dist-info/RECORD
falcon_auth-1.0.3.dist-info/WHEEL
falcon_auth-1.0.3.dist-info/metadata.json
falcon_auth-1.0.3.dist-info/top_level.txt
