Metadata-Version: 2.0
Name: falcon-auth
Version: 1.0.3
Summary: falcon-auth
Home-page: https://github.com/loanzen/falcon-auth
Author: Ritesh Kadmawala
Author-email: ritesh@loanzen.in
License: MIT
Platform: UNKNOWN
Requires-Dist: falcon
Requires-Dist: pyjwt
